mrestimator/__init__.py
mrestimator/_version.py
mrestimator/coefficients.py
mrestimator/fit.py
mrestimator/input_output.py
mrestimator/simulate.py
mrestimator/utility.py
mrestimator/wrapper.py
mrestimator-0.2.0.dist-info/licenses/LICENSE
mrestimator-0.2.0.dist-info/METADATA
mrestimator-0.2.0.dist-info/WHEEL
mrestimator-0.2.0.dist-info/top_level.txt
mrestimator-0.2.0.dist-info/RECORD
