Metadata-Version: 2.4
Name: mrestimator
Version: 0.2.0
Summary: Toolbox for the Multistep Regression Estimator.
Author: The Priesemann Group
Author-email: Paul Spitzner <paul.spitzner@ds.mpg.de>, Jonas Dehning <jonas.dehning@ds.mpg.de>
Project-URL: Homepage, https://github.com/Priesemann-Group/mrestimator
Project-URL: Bug Tracker, https://github.com/Priesemann-Group/mrestimator/issues
Classifier: License :: OSI Approved :: BSD License
Classifier: Operating System :: OS Independent
Classifier: Programming Language :: Python
Classifier: Programming Language :: Python :: 3
Classifier: Programming Language :: Python :: 3 :: Only
Classifier: Programming Language :: Python :: 3.10
Classifier: Programming Language :: Python :: 3.11
Classifier: Programming Language :: Python :: 3.12
Requires-Python: >=3.10.0
License-File: LICENSE
Requires-Dist: numpy>=1.11
Requires-Dist: scipy>=1.0.0
Requires-Dist: matplotlib>=1.7.0
Provides-Extra: full
Requires-Dist: numba>=0.44; extra == "full"
Requires-Dist: tqdm; extra == "full"
Provides-Extra: numba
Requires-Dist: numba>=0.44; extra == "numba"
Provides-Extra: docs
Requires-Dist: sphinx>=8.0.0; extra == "docs"
Requires-Dist: sphinx-rtd-theme; extra == "docs"
Requires-Dist: myst-parser; extra == "docs"
Requires-Dist: nbsphinx; extra == "docs"
Requires-Dist: sphinx-autodoc-typehints; extra == "docs"
Requires-Dist: sphinx-mdinclude; extra == "docs"
Requires-Dist: pandoc; extra == "docs"
Provides-Extra: dev
Requires-Dist: mrestimator[full]; extra == "dev"
Requires-Dist: mrestimator[docs]; extra == "dev"
Requires-Dist: pre-commit>=3.3.2; extra == "dev"
Requires-Dist: ruff>=0.0.272; extra == "dev"
Requires-Dist: pytest>=7.4.0; extra == "dev"
Requires-Dist: pytest-xdist>=3.5.0; extra == "dev"
Dynamic: license-file
